README.md
setup.cfg
setup.py
yahoo_finance/__init__.py
yahoo_finance/api.py
yahoo_finance/utils.py
yahoo_finance_api.egg-info/PKG-INFO
yahoo_finance_api.egg-info/SOURCES.txt
yahoo_finance_api.egg-info/dependency_links.txt
yahoo_finance_api.egg-info/requires.txt
yahoo_finance_api.egg-info/top_level.txt