Metadata-Version: 1.1
Name: yahoo-finance-api
Version: 0.5
Summary: Package to source data from Yahoo Finance
Home-page: https://github.com/rakeshbhat9/yahoo-finance-api
Author: Rakesh Bhat
Author-email: rakeshbhat9@gmail.com
License: UNKNOWN
Download-URL: https://github.com/rakeshbhat9/yahoo-finance-api/archive/v0.2.tar.gz
Keywords: v0.5
Platform: UNKNOWN
